{
  "tw" : {
    "Director" : "導演",
    "Label" : "類型",
    "Actor" : "演員",
    "Introdution" : "簡介",
    "Play" : "播放",
    "Preview" : "試看",
    "Pay" : "付費",
  },

　"cn" : {
    "Director" : "导演",
    "Label" : "类型",
    "Actor" : "演员",
    "Introdution" : "简介",
    "Play" : "播放",	
    "Preview" : "试看",
    "Pay" : "付费",
},

  "jp" : {
    "Director" : "ディレクター",
    "Label" : "タイプ",
    "Actor" : "俳優",
    "Introdution" : "簡単な紹介",
    "Play" : "ブロードキャスト",
    "Preview" : "見て",
    "Pay" : "支払い",
},

  "en" : {
    "Director" : " Director ",
    "Label" : " Label ",
    "Actor" : " Actor ",
    "Introdution" : " Introdution ",
    "Play" : " Play ",
    "Preview" : " Preview ",
    "Pay" : " Pay ",
  },

  "kr" : {
    "Director" : "이사",
    "Label" : "유형",
    "Actor" : "배우",
    "Introdution" : "간략한 소개",
    "Play" : "방송",
    "Preview" : "보기",
    "Pay" : "지불",
  },

}
